ontoportal_client/__init__.py
ontoportal_client/api.py
ontoportal_client/constants.py
ontoportal_client/py.typed
ontoportal_client/version.py
ontoportal_client-0.0.4.dist-info/LICENSE
ontoportal_client-0.0.4.dist-info/METADATA
ontoportal_client-0.0.4.dist-info/WHEEL
ontoportal_client-0.0.4.dist-info/top_level.txt
ontoportal_client-0.0.4.dist-info/RECORD
